loghandlerzmq/__init__.py
loghandlerzmq-2019.4.1.dist-info/LICENSE
loghandlerzmq-2019.4.1.dist-info/METADATA
loghandlerzmq-2019.4.1.dist-info/WHEEL
loghandlerzmq-2019.4.1.dist-info/top_level.txt
loghandlerzmq-2019.4.1.dist-info/RECORD
