Metadata-Version: 2.1
Name: loghandlerzmq
Version: 2019.4.1
Summary: Logging handler to transmit messages over zmq
Home-page: https://github.com/cjrh/loghandlerzmq
Author: Caleb Hattingh
Author-email: caleb.hattingh@gmail.com
License: UNKNOWN
Keywords: logging zmq
Platform: UNKNOWN
Classifier: Development Status :: 3 - Alpha
Classifier: Intended Audience :: Developers
Classifier: Topic :: System :: Logging
Classifier: Programming Language :: Python :: 3
Classifier: Programming Language :: Python :: 3.6
Classifier: Programming Language :: Python :: 3.7
Requires-Dist: pyzmq
Provides-Extra: dev
Requires-Dist: check-manifest ; extra == 'dev'
Provides-Extra: test
Requires-Dist: coverage ; extra == 'test'
